nest/__init__.py
nest/clean_up.py
nest/config.json
nest/config.py
nest/exception.py
nest/global_variables.py
nest/logging_helper.py
nest/mpeg_dash_encoder.py
nest/network_utilities.py
nest/topology_map.py
nest/user.py
nest/version.py
nest/engine/__init__.py
nest/engine/arp.py
nest/engine/coap.py
nest/engine/coap_client.py
nest/engine/coap_server.py
nest/engine/dynamic_routing.py
nest/engine/ethtool.py
nest/engine/exec.py
nest/engine/http_server.py
nest/engine/ip_address.py
nest/engine/ip_link.py
nest/engine/ip_mpls_route.py
nest/engine/ip_netns.py
nest/engine/ip_route.py
nest/engine/iperf3.py
nest/engine/ipv6_states.py
nest/engine/iterators.py
nest/engine/mpeg_dash.py
nest/engine/mptcp.py
nest/engine/netperf.py
nest/engine/ping.py
nest/engine/setns.py
nest/engine/sip.py
nest/engine/sysctl.py
nest/engine/t_shark.py
nest/engine/tc.py
nest/engine/tcp_modules.py
nest/engine/uname.py
nest/engine/util.py
nest/experiment/__init__.py
nest/experiment/experiment.py
nest/experiment/interrupts.py
nest/experiment/pack.py
nest/experiment/results.py
nest/experiment/run_exp.py
nest/experiment/tools.py
nest/experiment/constants/__init__.py
nest/experiment/constants/tcp_congestion_control_algorithms.py
nest/experiment/helpers/__init__.py
nest/experiment/helpers/tcp_validations.py
nest/experiment/info/README.txt
nest/experiment/parser/__init__.py
nest/experiment/parser/coap.py
nest/experiment/parser/iperf3.py
nest/experiment/parser/mpeg_dash.py
nest/experiment/parser/netperf.py
nest/experiment/parser/ping.py
nest/experiment/parser/runnerbase.py
nest/experiment/parser/sip.py
nest/experiment/parser/ss.py
nest/experiment/parser/tc.py
nest/experiment/parser/iterators/ss.sh
nest/experiment/parser/iterators/tc.sh
nest/experiment/plotter/__init__.py
nest/experiment/plotter/common.py
nest/experiment/plotter/iperf3.py
nest/experiment/plotter/mpeg_dash.py
nest/experiment/plotter/netperf.py
nest/experiment/plotter/ping.py
nest/experiment/plotter/seaborn-v0_8-paper.mplstyle
nest-0.4.4.dist-info/AUTHORS.txt
nest-0.4.4.dist-info/LICENSE
nest-0.4.4.dist-info/METADATA
nest-0.4.4.dist-info/WHEEL
nest-0.4.4.dist-info/top_level.txt
nest-0.4.4.dist-info/RECORD
