Metadata-Version: 2.1
Name: nest
Version: 0.4.4
Summary: NeST: Network Stack Tester
Home-page: https://nest.nitk.ac.in/
Author: NITK
Author-email: nest@nitk.edu.in
Project-URL: Source, https://gitlab.com/nitk-nest/nest
Keywords: network,namespace,linux
Classifier: Development Status :: 4 - Beta
Classifier: Intended Audience :: Developers
Classifier: Intended Audience :: Education
Classifier: Intended Audience :: Science/Research
Classifier: Intended Audience :: System Administrators
Classifier: Topic :: Education
Classifier: Topic :: Scientific/Engineering
Classifier: License :: OSI Approved :: GNU General Public License v2 (GPLv2)
Classifier: Operating System :: POSIX :: Linux
Classifier: Programming Language :: Python :: 3
Classifier: Programming Language :: Python :: 3.6
Classifier: Programming Language :: Python :: 3.7
Classifier: Programming Language :: Python :: 3.8
Requires-Python: >=3.6, <4
License-File: LICENSE
License-File: AUTHORS.txt
Requires-Dist: matplotlib
Requires-Dist: numpy
Requires-Dist: packaging
Requires-Dist: tqdm
Requires-Dist: aiocoap
Requires-Dist: colorama
